checksec/__init__.py
checksec/__main__.py
checksec/binary.py
checksec/elf.py
checksec/errors.py
checksec/output.py
checksec/pe.py
checksec/utils.py
checksec_py-0.7.5.dist-info/LICENSE
checksec_py-0.7.5.dist-info/METADATA
checksec_py-0.7.5.dist-info/WHEEL
checksec_py-0.7.5.dist-info/entry_points.txt
checksec_py-0.7.5.dist-info/RECORD
