Metadata-Version: 2.3
Name: checksec-py
Version: 0.7.5
Summary: Checksec tool implemented in Python
License: GPL-3.0-only
Keywords: checksec,security,ELF,PE,binary
Author: Mathieu Tarral
Author-email: mathieu.tarral@protonmail.com
Requires-Python: >=3.10,<3.14.0
Classifier: License :: OSI Approved :: GNU General Public License v3 (GPLv3)
Classifier: Programming Language :: Python :: 3
Classifier: Programming Language :: Python :: 3.10
Classifier: Programming Language :: Python :: 3.11
Classifier: Programming Language :: Python :: 3.12
Classifier: Programming Language :: Python :: 3.13
Requires-Dist: docopt (==0.6.2)
Requires-Dist: lief (==0.16.6)
Requires-Dist: pylddwrap (>=1.2.2,<2.0.0)
Requires-Dist: rich (>=14.0.0,<15.0.0)
Project-URL: Repository, https://github.com/Wenzel/checksec.py
